kopylot/__init__.py
kopylot/audit.py
kopylot/chat.py
kopylot/cli.py
kopylot/diagnose.py
kopylot/llm.py
kopylot/prompts.py
kopylot/utils.py
kopylot/version.py
kopylot_gpt-0.0.3.dist-info/LICENSE
kopylot_gpt-0.0.3.dist-info/METADATA
kopylot_gpt-0.0.3.dist-info/WHEEL
kopylot_gpt-0.0.3.dist-info/entry_points.txt
kopylot_gpt-0.0.3.dist-info/RECORD
