Metadata-Version: 2.1
Name: kopylot-gpt
Version: 0.0.3
Summary: Your AI Powered Kubernetes Assistant from Thiago Alves with fix text-davinci-003
Home-page: https://github.com/hoalongnatsu/kopylot
Author: hoalongnatsu
Requires-Python: >=3.8,<4.0
Classifier: Programming Language :: Python :: 3
Classifier: Programming Language :: Python :: 3.8
Classifier: Programming Language :: Python :: 3.9
Classifier: Programming Language :: Python :: 3.10
Classifier: Programming Language :: Python :: 3.11
Classifier: Programming Language :: Python :: 3.12
Requires-Dist: inquirerpy (>=0.3.4,<0.4.0)
Requires-Dist: openai (>=0.27.2,<0.28.0)
Requires-Dist: rich (>=13.3.3,<14.0.0)
Requires-Dist: typer (>=0.7.0,<0.8.0)
Project-URL: Documentation, https://github.com/hoalongnatsu/kopylot
Project-URL: Repository, https://github.com/hoalongnatsu/kopylot
